SmartFileSorter-0.4.0.data/scripts/sfs
SmartFileSorter-0.4.0.dist-info/RECORD
SmartFileSorter-0.4.0.dist-info/top_level.txt
SmartFileSorter-0.4.0.dist-info/metadata.json
SmartFileSorter-0.4.0.dist-info/DESCRIPTION.rst
SmartFileSorter-0.4.0.dist-info/WHEEL
SmartFileSorter-0.4.0.dist-info/METADATA
smartfilesorter/__init__.py
smartfilesorter/ruleset.py
smartfilesorter/smartfilesorter.py
smartfilesorter/exceptions.py
smartfilesorter/matchplugins/filenamestartswith.py
smartfilesorter/matchplugins/__init__.py
smartfilesorter/matchplugins/filenamecontains.py
smartfilesorter/matchplugins/filenamematches.py
smartfilesorter/matchplugins/filenameendswith.py
smartfilesorter/matchplugins/fileextensionis.py
smartfilesorter/actionplugins/stopprocessing.py
smartfilesorter/actionplugins/__init__.py
smartfilesorter/actionplugins/renameto.py
smartfilesorter/actionplugins/moveto.py
smartfilesorter/actionplugins/printfileinfo.py
