Metadata-Version: 2.0
Name: SmartFileSorter
Version: 0.4.0
Summary: Rule based file moving and renaming tool
Home-page: https://github.com/jashort/SmartFileSorter
Author: Jason Short
Author-email: jason@sheersky.com
License: BSD
Keywords: smartfilesorter
Platform: UNKNOWN
Classifier: Development Status :: 2 - Pre-Alpha
Classifier: Intended Audience :: Developers
Classifier: Intended Audience :: System Administrators
Classifier: License :: OSI Approved :: BSD License
Classifier: Natural Language :: English
Classifier: Programming Language :: Python :: 2
Classifier: Programming Language :: Python :: 2.7
Classifier: Programming Language :: Python :: 3
Classifier: Programming Language :: Python :: 3.3
Classifier: Programming Language :: Python :: 3.4
Classifier: Topic :: Utilities
Requires-Dist: wheel
Requires-Dist: PyYAML
Requires-Dist: docopt
